rummy/__init__.py
rummy/__main__.py
rummy/constants/__init__.py
rummy/constants/constants.py
rummy/constants/resource_path.py
rummy/controller/__init__.py
rummy/controller/ai_controller.py
rummy/controller/human_controller.py
rummy/controller/player_controller.py
rummy/deck/__init__.py
rummy/deck/card.py
rummy/deck/deck.py
rummy/deck/face_values.py
rummy/deck/rank.py
rummy/deck/sort.py
rummy/deck/suits.py
rummy/exception/__init__.py
rummy/exception/validation_error.py
rummy/game/__init__.py
rummy/game/melds.py
rummy/game/players.py
rummy/game/round.py
rummy/game/score.py
rummy/play.py
rummy/player/__init__.py
rummy/player/ai.py
rummy/player/dealer.py
rummy/player/hand.py
rummy/player/human.py
rummy/player/player.py
rummy/templates/ai-discard-data.txt
rummy/templates/ai-hand-data.txt
rummy/templates/ai-thinking.txt
rummy/templates/ai-turn-end.txt
rummy/templates/blank.txt
rummy/templates/hand-score.txt
rummy/templates/knocked.txt
rummy/templates/player-discarded.txt
rummy/templates/player-turn-end.txt
rummy/templates/player-turn-start.txt
rummy/templates/round-end.txt
rummy/templates/turn-start.txt
rummy/ui/__init__.py
rummy/ui/action.py
rummy/ui/action_collection.py
rummy/ui/menu_action_dialog.py
rummy/ui/player_action_dialog.py
rummy/ui/user_input.py
rummy/ui/view.py
rummy/view/__init__.py
rummy/view/ai_view.py
rummy/view/human_view.py
rummy/view/player_view.py
rummy/view/round_view.py
rummy-2.1.5.dist-info/entry_points.txt
rummy-2.1.5.dist-info/LICENSE.txt
rummy-2.1.5.dist-info/WHEEL
rummy-2.1.5.dist-info/METADATA
rummy-2.1.5.dist-info/RECORD
